cpypes/__init__.py
cpypes/__main__.py
cpypes/carray.py
cpypes/cpointer.py
cpypes/cpype.py
cpypes/cstruct.py
cpypes/install.py
cpypes/simple_types.py
cpypes/data/server.tar.gz
cpypes-0.0.1.dist-info/LICENSE
cpypes-0.0.1.dist-info/METADATA
cpypes-0.0.1.dist-info/WHEEL
cpypes-0.0.1.dist-info/top_level.txt
cpypes-0.0.1.dist-info/RECORD
