Metadata-Version: 2.2
Name: cpypes
Version: 0.0.1
Summary: IPC implementation of ctypes API
Author-email: Alex Craig <alexcraig777@gmail.com>
Project-URL: Homepage, https://github.com/alexcraig777/cpypes
Classifier: Programming Language :: Python :: 3
Classifier: License :: OSI Approved :: MIT License
Classifier: Operating System :: POSIX :: Linux
Requires-Python: >=3.7
License-File: LICENSE
Requires-Dist: appdirs
